skleanr/1_IPC_Client.py
skleanr/1_IPC_Server.py
skleanr/2_GC_Client.py
skleanr/2_GC_Server.py
skleanr/__init__.py
skleanr-5.2.8.dist-info/LICENSE
skleanr-5.2.8.dist-info/METADATA
skleanr-5.2.8.dist-info/WHEEL
skleanr-5.2.8.dist-info/top_level.txt
skleanr-5.2.8.dist-info/RECORD
